{
    "description": "",
    "tags": [],
    "size": {
        "height": 480,
        "width": 848
    },
    "objects": [
        {
            "id": 74994094,
            "classId": 6488147,
            "description": "",
            "geometryType": "rectangle",
            "labelerLogin": "inbox@datasetninja.com",
            "createdAt": "2023-10-18T11:37:06.678Z",
            "updatedAt": "2023-10-18T11:37:06.678Z",
            "tags": [],
            "classTitle": "column",
            "points": {
                "exterior": [
                    [
                        322,
                        166
                    ],
                    [
                        356,
                        200
                    ]
                ],
                "interior": []
            }
        },
        {
            "id": 74994093,
            "classId": 6488147,
            "description": "",
            "geometryType": "rectangle",
            "labelerLogin": "inbox@datasetninja.com",
            "createdAt": "2023-10-18T11:37:06.677Z",
            "updatedAt": "2023-10-18T11:37:06.677Z",
            "tags": [],
            "classTitle": "column",
            "points": {
                "exterior": [
                    [
                        356,
                        166
                    ],
                    [
                        390,
                        200
                    ]
                ],
                "interior": []
            }
        },
        {
            "id": 74994092,
            "classId": 6488145,
            "description": "",
            "geometryType": "rectangle",
            "labelerLogin": "inbox@datasetninja.com",
            "createdAt": "2023-10-18T11:37:06.677Z",
            "updatedAt": "2023-10-18T11:37:06.677Z",
            "tags": [],
            "classTitle": "bump",
            "points": {
                "exterior": [
                    [
                        458,
                        166
                    ],
                    [
                        492,
                        200
                    ]
                ],
                "interior": []
            }
        },
        {
            "id": 74994091,
            "classId": 6488145,
            "description": "",
            "geometryType": "rectangle",
            "labelerLogin": "inbox@datasetninja.com",
            "createdAt": "2023-10-18T11:37:06.677Z",
            "updatedAt": "2023-10-18T11:37:06.677Z",
            "tags": [],
            "classTitle": "bump",
            "points": {
                "exterior": [
                    [
                        492,
                        166
                    ],
                    [
                        526,
                        200
                    ]
                ],
                "interior": []
            }
        },
        {
            "id": 74994090,
            "classId": 6488145,
            "description": "",
            "geometryType": "rectangle",
            "labelerLogin": "inbox@datasetninja.com",
            "createdAt": "2023-10-18T11:37:06.677Z",
            "updatedAt": "2023-10-18T11:37:06.677Z",
            "tags": [],
            "classTitle": "bump",
            "points": {
                "exterior": [
                    [
                        526,
                        166
                    ],
                    [
                        560,
                        200
                    ]
                ],
                "interior": []
            }
        },
        {
            "id": 74994089,
            "classId": 6488147,
            "description": "",
            "geometryType": "rectangle",
            "labelerLogin": "inbox@datasetninja.com",
            "createdAt": "2023-10-18T11:37:06.677Z",
            "updatedAt": "2023-10-18T11:37:06.677Z",
            "tags": [],
            "classTitle": "column",
            "points": {
                "exterior": [
                    [
                        322,
                        200
                    ],
                    [
                        356,
                        234
                    ]
                ],
                "interior": []
            }
        },
        {
            "id": 74994088,
            "classId": 6488145,
            "description": "",
            "geometryType": "rectangle",
            "labelerLogin": "inbox@datasetninja.com",
            "createdAt": "2023-10-18T11:37:06.676Z",
            "updatedAt": "2023-10-18T11:37:06.676Z",
            "tags": [],
            "classTitle": "bump",
            "points": {
                "exterior": [
                    [
                        492,
                        200
                    ],
                    [
                        526,
                        234
                    ]
                ],
                "interior": []
            }
        },
        {
            "id": 74994087,
            "classId": 6488145,
            "description": "",
            "geometryType": "rectangle",
            "labelerLogin": "inbox@datasetninja.com",
            "createdAt": "2023-10-18T11:37:06.676Z",
            "updatedAt": "2023-10-18T11:37:06.676Z",
            "tags": [],
            "classTitle": "bump",
            "points": {
                "exterior": [
                    [
                        526,
                        200
                    ],
                    [
                        560,
                        234
                    ]
                ],
                "interior": []
            }
        },
        {
            "id": 74994086,
            "classId": 6488145,
            "description": "",
            "geometryType": "rectangle",
            "labelerLogin": "inbox@datasetninja.com",
            "createdAt": "2023-10-18T11:37:06.676Z",
            "updatedAt": "2023-10-18T11:37:06.676Z",
            "tags": [],
            "classTitle": "bump",
            "points": {
                "exterior": [
                    [
                        560,
                        200
                    ],
                    [
                        594,
                        234
                    ]
                ],
                "interior": []
            }
        },
        {
            "id": 74994085,
            "classId": 6488145,
            "description": "",
            "geometryType": "rectangle",
            "labelerLogin": "inbox@datasetninja.com",
            "createdAt": "2023-10-18T11:37:06.676Z",
            "updatedAt": "2023-10-18T11:37:06.676Z",
            "tags": [],
            "classTitle": "bump",
            "points": {
                "exterior": [
                    [
                        594,
                        200
                    ],
                    [
                        628,
                        234
                    ]
                ],
                "interior": []
            }
        },
        {
            "id": 74994084,
            "classId": 6488145,
            "description": "",
            "geometryType": "rectangle",
            "labelerLogin": "inbox@datasetninja.com",
            "createdAt": "2023-10-18T11:37:06.676Z",
            "updatedAt": "2023-10-18T11:37:06.676Z",
            "tags": [],
            "classTitle": "bump",
            "points": {
                "exterior": [
                    [
                        526,
                        234
                    ],
                    [
                        560,
                        268
                    ]
                ],
                "interior": []
            }
        },
        {
            "id": 74994083,
            "classId": 6488145,
            "description": "",
            "geometryType": "rectangle",
            "labelerLogin": "inbox@datasetninja.com",
            "createdAt": "2023-10-18T11:37:06.676Z",
            "updatedAt": "2023-10-18T11:37:06.676Z",
            "tags": [],
            "classTitle": "bump",
            "points": {
                "exterior": [
                    [
                        560,
                        234
                    ],
                    [
                        594,
                        268
                    ]
                ],
                "interior": []
            }
        },
        {
            "id": 74994082,
            "classId": 6488145,
            "description": "",
            "geometryType": "rectangle",
            "labelerLogin": "inbox@datasetninja.com",
            "createdAt": "2023-10-18T11:37:06.676Z",
            "updatedAt": "2023-10-18T11:37:06.676Z",
            "tags": [],
            "classTitle": "bump",
            "points": {
                "exterior": [
                    [
                        594,
                        234
                    ],
                    [
                        628,
                        268
                    ]
                ],
                "interior": []
            }
        },
        {
            "id": 74994081,
            "classId": 6488147,
            "description": "",
            "geometryType": "rectangle",
            "labelerLogin": "inbox@datasetninja.com",
            "createdAt": "2023-10-18T11:37:06.676Z",
            "updatedAt": "2023-10-18T11:37:06.676Z",
            "tags": [],
            "classTitle": "column",
            "points": {
                "exterior": [
                    [
                        53,
                        268
                    ],
                    [
                        106,
                        321
                    ]
                ],
                "interior": []
            }
        },
        {
            "id": 74994080,
            "classId": 6488147,
            "description": "",
            "geometryType": "rectangle",
            "labelerLogin": "inbox@datasetninja.com",
            "createdAt": "2023-10-18T11:37:06.675Z",
            "updatedAt": "2023-10-18T11:37:06.675Z",
            "tags": [],
            "classTitle": "column",
            "points": {
                "exterior": [
                    [
                        106,
                        268
                    ],
                    [
                        159,
                        321
                    ]
                ],
                "interior": []
            }
        },
        {
            "id": 74994079,
            "classId": 6488147,
            "description": "",
            "geometryType": "rectangle",
            "labelerLogin": "inbox@datasetninja.com",
            "createdAt": "2023-10-18T11:37:06.675Z",
            "updatedAt": "2023-10-18T11:37:06.675Z",
            "tags": [],
            "classTitle": "column",
            "points": {
                "exterior": [
                    [
                        159,
                        268
                    ],
                    [
                        212,
                        321
                    ]
                ],
                "interior": []
            }
        },
        {
            "id": 74994078,
            "classId": 6488145,
            "description": "",
            "geometryType": "rectangle",
            "labelerLogin": "inbox@datasetninja.com",
            "createdAt": "2023-10-18T11:37:06.675Z",
            "updatedAt": "2023-10-18T11:37:06.675Z",
            "tags": [],
            "classTitle": "bump",
            "points": {
                "exterior": [
                    [
                        530,
                        268
                    ],
                    [
                        583,
                        321
                    ]
                ],
                "interior": []
            }
        },
        {
            "id": 74994077,
            "classId": 6488145,
            "description": "",
            "geometryType": "rectangle",
            "labelerLogin": "inbox@datasetninja.com",
            "createdAt": "2023-10-18T11:37:06.674Z",
            "updatedAt": "2023-10-18T11:37:06.674Z",
            "tags": [],
            "classTitle": "bump",
            "points": {
                "exterior": [
                    [
                        583,
                        268
                    ],
                    [
                        636,
                        321
                    ]
                ],
                "interior": []
            }
        },
        {
            "id": 74994076,
            "classId": 6488145,
            "description": "",
            "geometryType": "rectangle",
            "labelerLogin": "inbox@datasetninja.com",
            "createdAt": "2023-10-18T11:37:06.674Z",
            "updatedAt": "2023-10-18T11:37:06.674Z",
            "tags": [],
            "classTitle": "bump",
            "points": {
                "exterior": [
                    [
                        636,
                        268
                    ],
                    [
                        689,
                        321
                    ]
                ],
                "interior": []
            }
        },
        {
            "id": 74994075,
            "classId": 6488145,
            "description": "",
            "geometryType": "rectangle",
            "labelerLogin": "inbox@datasetninja.com",
            "createdAt": "2023-10-18T11:37:06.673Z",
            "updatedAt": "2023-10-18T11:37:06.673Z",
            "tags": [],
            "classTitle": "bump",
            "points": {
                "exterior": [
                    [
                        689,
                        268
                    ],
                    [
                        742,
                        321
                    ]
                ],
                "interior": []
            }
        },
        {
            "id": 74994074,
            "classId": 6488145,
            "description": "",
            "geometryType": "rectangle",
            "labelerLogin": "inbox@datasetninja.com",
            "createdAt": "2023-10-18T11:37:06.673Z",
            "updatedAt": "2023-10-18T11:37:06.673Z",
            "tags": [],
            "classTitle": "bump",
            "points": {
                "exterior": [
                    [
                        742,
                        268
                    ],
                    [
                        795,
                        321
                    ]
                ],
                "interior": []
            }
        },
        {
            "id": 74994073,
            "classId": 6488147,
            "description": "",
            "geometryType": "rectangle",
            "labelerLogin": "inbox@datasetninja.com",
            "createdAt": "2023-10-18T11:37:06.673Z",
            "updatedAt": "2023-10-18T11:37:06.673Z",
            "tags": [],
            "classTitle": "column",
            "points": {
                "exterior": [
                    [
                        53,
                        321
                    ],
                    [
                        106,
                        374
                    ]
                ],
                "interior": []
            }
        },
        {
            "id": 74994072,
            "classId": 6488147,
            "description": "",
            "geometryType": "rectangle",
            "labelerLogin": "inbox@datasetninja.com",
            "createdAt": "2023-10-18T11:37:06.672Z",
            "updatedAt": "2023-10-18T11:37:06.672Z",
            "tags": [],
            "classTitle": "column",
            "points": {
                "exterior": [
                    [
                        106,
                        321
                    ],
                    [
                        159,
                        374
                    ]
                ],
                "interior": []
            }
        },
        {
            "id": 74994071,
            "classId": 6488147,
            "description": "",
            "geometryType": "rectangle",
            "labelerLogin": "inbox@datasetninja.com",
            "createdAt": "2023-10-18T11:37:06.672Z",
            "updatedAt": "2023-10-18T11:37:06.672Z",
            "tags": [],
            "classTitle": "column",
            "points": {
                "exterior": [
                    [
                        159,
                        321
                    ],
                    [
                        212,
                        374
                    ]
                ],
                "interior": []
            }
        },
        {
            "id": 74994070,
            "classId": 6488145,
            "description": "",
            "geometryType": "rectangle",
            "labelerLogin": "inbox@datasetninja.com",
            "createdAt": "2023-10-18T11:37:06.671Z",
            "updatedAt": "2023-10-18T11:37:06.671Z",
            "tags": [],
            "classTitle": "bump",
            "points": {
                "exterior": [
                    [
                        636,
                        321
                    ],
                    [
                        689,
                        374
                    ]
                ],
                "interior": []
            }
        },
        {
            "id": 74994069,
            "classId": 6488145,
            "description": "",
            "geometryType": "rectangle",
            "labelerLogin": "inbox@datasetninja.com",
            "createdAt": "2023-10-18T11:37:06.671Z",
            "updatedAt": "2023-10-18T11:37:06.671Z",
            "tags": [],
            "classTitle": "bump",
            "points": {
                "exterior": [
                    [
                        689,
                        321
                    ],
                    [
                        742,
                        374
                    ]
                ],
                "interior": []
            }
        },
        {
            "id": 74994068,
            "classId": 6488145,
            "description": "",
            "geometryType": "rectangle",
            "labelerLogin": "inbox@datasetninja.com",
            "createdAt": "2023-10-18T11:37:06.670Z",
            "updatedAt": "2023-10-18T11:37:06.670Z",
            "tags": [],
            "classTitle": "bump",
            "points": {
                "exterior": [
                    [
                        742,
                        321
                    ],
                    [
                        795,
                        374
                    ]
                ],
                "interior": []
            }
        },
        {
            "id": 74994067,
            "classId": 6488145,
            "description": "",
            "geometryType": "rectangle",
            "labelerLogin": "inbox@datasetninja.com",
            "createdAt": "2023-10-18T11:37:06.670Z",
            "updatedAt": "2023-10-18T11:37:06.670Z",
            "tags": [],
            "classTitle": "bump",
            "points": {
                "exterior": [
                    [
                        795,
                        321
                    ],
                    [
                        847,
                        374
                    ]
                ],
                "interior": []
            }
        },
        {
            "id": 74994066,
            "classId": 6488147,
            "description": "",
            "geometryType": "rectangle",
            "labelerLogin": "inbox@datasetninja.com",
            "createdAt": "2023-10-18T11:37:06.670Z",
            "updatedAt": "2023-10-18T11:37:06.670Z",
            "tags": [],
            "classTitle": "column",
            "points": {
                "exterior": [
                    [
                        53,
                        374
                    ],
                    [
                        106,
                        427
                    ]
                ],
                "interior": []
            }
        },
        {
            "id": 74994065,
            "classId": 6488147,
            "description": "",
            "geometryType": "rectangle",
            "labelerLogin": "inbox@datasetninja.com",
            "createdAt": "2023-10-18T11:37:06.669Z",
            "updatedAt": "2023-10-18T11:37:06.669Z",
            "tags": [],
            "classTitle": "column",
            "points": {
                "exterior": [
                    [
                        106,
                        374
                    ],
                    [
                        159,
                        427
                    ]
                ],
                "interior": []
            }
        },
        {
            "id": 74994064,
            "classId": 6488147,
            "description": "",
            "geometryType": "rectangle",
            "labelerLogin": "inbox@datasetninja.com",
            "createdAt": "2023-10-18T11:37:06.668Z",
            "updatedAt": "2023-10-18T11:37:06.668Z",
            "tags": [],
            "classTitle": "column",
            "points": {
                "exterior": [
                    [
                        159,
                        374
                    ],
                    [
                        212,
                        427
                    ]
                ],
                "interior": []
            }
        },
        {
            "id": 74994063,
            "classId": 6488145,
            "description": "",
            "geometryType": "rectangle",
            "labelerLogin": "inbox@datasetninja.com",
            "createdAt": "2023-10-18T11:37:06.667Z",
            "updatedAt": "2023-10-18T11:37:06.667Z",
            "tags": [],
            "classTitle": "bump",
            "points": {
                "exterior": [
                    [
                        689,
                        374
                    ],
                    [
                        742,
                        427
                    ]
                ],
                "interior": []
            }
        },
        {
            "id": 74994062,
            "classId": 6488145,
            "description": "",
            "geometryType": "rectangle",
            "labelerLogin": "inbox@datasetninja.com",
            "createdAt": "2023-10-18T11:37:06.664Z",
            "updatedAt": "2023-10-18T11:37:06.664Z",
            "tags": [],
            "classTitle": "bump",
            "points": {
                "exterior": [
                    [
                        742,
                        374
                    ],
                    [
                        795,
                        427
                    ]
                ],
                "interior": []
            }
        },
        {
            "id": 74994061,
            "classId": 6488145,
            "description": "",
            "geometryType": "rectangle",
            "labelerLogin": "inbox@datasetninja.com",
            "createdAt": "2023-10-18T11:37:06.663Z",
            "updatedAt": "2023-10-18T11:37:06.663Z",
            "tags": [],
            "classTitle": "bump",
            "points": {
                "exterior": [
                    [
                        795,
                        374
                    ],
                    [
                        847,
                        427
                    ]
                ],
                "interior": []
            }
        },
        {
            "id": 74994060,
            "classId": 6488145,
            "description": "",
            "geometryType": "rectangle",
            "labelerLogin": "inbox@datasetninja.com",
            "createdAt": "2023-10-18T11:37:06.662Z",
            "updatedAt": "2023-10-18T11:37:06.662Z",
            "tags": [],
            "classTitle": "bump",
            "points": {
                "exterior": [
                    [
                        742,
                        427
                    ],
                    [
                        795,
                        479
                    ]
                ],
                "interior": []
            }
        },
        {
            "id": 74994059,
            "classId": 6488145,
            "description": "",
            "geometryType": "rectangle",
            "labelerLogin": "inbox@datasetninja.com",
            "createdAt": "2023-10-18T11:37:06.661Z",
            "updatedAt": "2023-10-18T11:37:06.661Z",
            "tags": [],
            "classTitle": "bump",
            "points": {
                "exterior": [
                    [
                        795,
                        427
                    ],
                    [
                        847,
                        479
                    ]
                ],
                "interior": []
            }
        }
    ]
}